color_craftsman/__init__.py
color_craftsman/color_utils/__init__.py
color_craftsman/color_utils/color_space.py
color_craftsman/math/__init__.py
color_craftsman/math/utils.py
color_craftsman/palette_generation.py
color_craftsman/visualization.py
color_craftsman-0.1.0.dist-info/LICENSE
color_craftsman-0.1.0.dist-info/METADATA
color_craftsman-0.1.0.dist-info/WHEEL
color_craftsman-0.1.0.dist-info/RECORD
