Metadata-Version: 2.1
Name: color-craftsman
Version: 0.1.0
Summary: Perceptually-distinct color palette generator for data visualization in Python.
Home-page: https://github.com/caharper/color-craftsman
License: MIT
Keywords: data visualization,color palette,perceptual distinctiveness,color-blind safe,visualization tools,python,color theory,accessible visualizations
Author: Clay Harper
Author-email: caharper@smu.edu
Requires-Python: >=3.9
Classifier: Intended Audience :: Science/Research
Classifier: License :: OSI Approved :: MIT License
Classifier: Programming Language :: Python :: 3
Classifier: Programming Language :: Python :: 3.9
Classifier: Programming Language :: Python :: 3.10
Classifier: Programming Language :: Python :: 3.11
Classifier: Programming Language :: Python :: 3.12
Classifier: Topic :: Scientific/Engineering
Classifier: Topic :: Scientific/Engineering :: Artificial Intelligence
Classifier: Topic :: Scientific/Engineering :: Visualization
Requires-Dist: colorspacious (>=1.1.2,<2.0.0)
Requires-Dist: matplotlib (>=3.8.2,<4.0.0)
Requires-Dist: numpy (>=1.19.2)
Project-URL: Repository, https://github.com/caharper/color-craftsman
